underbelly/__init__.py
underbelly/core.py
underbelly/envs/__init__.py
underbelly/envs/models/__init__.py
underbelly/envs/models/payloads.py
underbelly/envs/modules/__init__.py
underbelly/envs/modules/db/__init__.py
underbelly/envs/modules/db/core.py
underbelly/envs/modules/db/placeholder.py
underbelly/envs/modules/episodes/__init__.py
underbelly/envs/modules/episodes/core.py
underbelly/envs/modules/metrics/__init__.py
underbelly/envs/modules/metrics/core.py
underbelly/envs/modules/opts/__init__.py
underbelly/envs/modules/opts/core.py
underbelly/envs/modules/opts/metric.py
underbelly/envs/modules/opts/models.py
underbelly/envs/modules/opts/time.py
underbelly/envs/modules/schemas/__init__.py
underbelly/envs/modules/schemas/core.py
underbelly/envs/modules/schemas/episode.py
underbelly/envs/modules/schemas/fields.py
underbelly/envs/modules/schemas/identifiers.py
underbelly/envs/modules/schemas/metrics.py
underbelly/envs/modules/schemas/user.py
underbelly/envs/utils/__init__.py
underbelly/envs/utils/_dicts.py
underbelly/envs/utils/_msg.py
underbelly/envs/utils/_stack.py
underbelly/envs/utils/_toolz.py
underbelly/envs/utils/_typing.py
underbelly/imports.py
underbelly/orders/__init__.py
underbelly/orders/broker.py
underbelly/orders/casters.py
underbelly/orders/executor.py
underbelly/orders/status.py
underbelly/orders/trade.py
underbelly/orders/trade_type.py
underbelly/orders/utils/__init__.py
underbelly/orders/utils/delimiters.py
underbelly/time.py
underbelly/valid.py
underbelly-0.0.1.dist-info/WHEEL
underbelly-0.0.1.dist-info/METADATA
underbelly-0.0.1.dist-info/RECORD
